swiftonhpss/__init__.py
swiftonhpss/swift/__init__.py
swiftonhpss/swift/common/__init__.py
swiftonhpss/swift/common/constraints.py
swiftonhpss/swift/common/exceptions.py
swiftonhpss/swift/common/fs_utils.py
swiftonhpss/swift/common/hpssfs_ioctl.py
swiftonhpss/swift/common/utils.py
swiftonhpss/swift/common/middleware/__init__.py
swiftonhpss/swift/common/middleware/check_constraints.py
swiftonhpss/swift/obj/__init__.py
swiftonhpss/swift/obj/diskfile.py
swiftonhpss/swift/obj/server.py
swiftonhpss-2.5.0.0.data/scripts/swiftonhpss-migrate-metadata
swiftonhpss-2.5.0.0.data/scripts/swiftonhpss-nstool
swiftonhpss-2.5.0.0.data/scripts/swiftonhpss-print-metadata
swiftonhpss-2.5.0.0.dist-info/DESCRIPTION.rst
swiftonhpss-2.5.0.0.dist-info/METADATA
swiftonhpss-2.5.0.0.dist-info/RECORD
swiftonhpss-2.5.0.0.dist-info/WHEEL
swiftonhpss-2.5.0.0.dist-info/entry_points.txt
swiftonhpss-2.5.0.0.dist-info/metadata.json
swiftonhpss-2.5.0.0.dist-info/top_level.txt
test/functional/__init__.py
test/functional/swift_on_file_tests.py
test/functional/swift_on_hpss_tests.py
test/functional/swift_test_client.py
test/functional/test_account.py
test/functional/test_container.py
test/functional/test_object.py
test/functional/tests.py
test/unit/__init__.py
test/unit/test_sof_pkg.py
test/unit/common/__init__.py
test/unit/common/test_constraints.py
test/unit/common/test_fs_utils.py
test/unit/common/test_utils.py
test/unit/common/middleware/__init__.py
test/unit/common/middleware/test_constraints.py
test/unit/obj/__init__.py
test/unit/obj/test_diskfile.py
test/unit/obj/test_server.py
