Metadata-Version: 2.0
Name: swiftonhpss
Version: 2.5.0.0
Summary: Swift-on-HPSS is a fork of the Swift-on-File Swift Object Server implementation that enables users to access the same data, both as an object and as a file. Data can be stored and retrieved through Swift's REST interface or as files from your site's HPSS archive system.
Home-page: https://github.com/openstack/swiftonhpss
Author: HPSS Collaboration
Author-email: UNKNOWN
License: Apache License (2.0)
Platform: UNKNOWN
Classifier: Development Status :: 3 - Alpha
Classifier: Environment :: OpenStack
Classifier: Intended Audience :: Information Technology
Classifier: Intended Audience :: System Administrators
Classifier: License :: OSI Approved :: Apache Software License
Classifier: Operating System :: POSIX :: Linux
Classifier: Programming Language :: Python
Classifier: Programming Language :: Python :: 2
Classifier: Programming Language :: Python :: 2.6
Classifier: Programming Language :: Python :: 2.7
